objectionpy/__init__.py
objectionpy/_utils.py
objectionpy/assets.py
objectionpy/enums.py
objectionpy/frames.py
objectionpy/objection.py
objectionpy/preset.py
objectionpy-0.0.4.dist-info/LICENSE.txt
objectionpy-0.0.4.dist-info/METADATA
objectionpy-0.0.4.dist-info/WHEEL
objectionpy-0.0.4.dist-info/top_level.txt
objectionpy-0.0.4.dist-info/RECORD
