Metadata-Version: 2.1
Name: objectionpy
Version: 0.0.4
Summary: A modular python library for creating objection.lol projects
Home-page: https://github.com/adamantii/objection.py
Author: Adamanti
Author-email: adam@sallome.com
Project-URL: Documentation, https://adamantii.github.io/objection.py
Project-URL: Bug Reports, https://github.com/adamantii/objection.py/issues
Project-URL: Source, https://github.com/adamantii/objection.py
Keywords: objection.lol,objection-lol,objectionlol,objection,generator,case,scene
Classifier: Topic :: Artistic Software
Classifier: License :: OSI Approved :: MIT License
Classifier: Development Status :: 4 - Beta
Classifier: Programming Language :: Python :: 3
Requires-Python: >=3.6
License-File: LICENSE.txt
Requires-Dist: requests
